printstyler/__init__.py
printstyler/__main__.py
printstyler/printstyler.py
printstyler-0.2.3.dist-info/LICENCE.txt
printstyler-0.2.3.dist-info/METADATA
printstyler-0.2.3.dist-info/WHEEL
printstyler-0.2.3.dist-info/top_level.txt
printstyler-0.2.3.dist-info/RECORD
