Metadata-Version: 2.1
Name: printstyler
Version: 0.2.3
Summary: The Printer package provides a simple way to print messages with ANSI colors and styles in Python.
Home-page: https://github.com/Jmofuture/printstyler
Author: Jean Olmedillo
Author-email: jeanolmedillo@outlook.com
Keywords: print,printer,printstyler
Classifier: Development Status :: 3 - Alpha
Classifier: Intended Audience :: Developers
Classifier: License :: OSI Approved :: MIT License
Classifier: Programming Language :: Python :: 3
Classifier: Programming Language :: Python :: 3.8
Classifier: Programming Language :: Python :: 3.9
Classifier: Programming Language :: Python :: 3.10
Classifier: Programming Language :: Python :: 3.11
Requires-Python: >=3.8
License-File: LICENCE.txt
